[
	{
		"__TYPE__": "SharedSliceContent",
		"variation": "default",
		"primary": {
			"heading": {
				"__TYPE__": "StructuredTextContent",
				"value": [
					{
						"type": "paragraph",
						"content": {
							"text": "Occaecat fugiat proident veniam incididunt esse sunt pariatur et ut amet. Non id laborum ullamco enim minim nulla quis est exercitation eiusmod labore do dolore. In fugiat fugiat ut est adipisicing enim."
						}
					}
				]
			},
			"quesans": {
				"__TYPE__": "GroupContentType",
				"value": [
					{
						"__TYPE__": "GroupItemContent",
						"value": [
							[
								"question",
								{
									"__TYPE__": "StructuredTextContent",
									"value": [
										{
											"type": "paragraph",
											"content": {
												"text": "Ipsum do exercitation cupidatat cupidatat sint cillum ut consectetur."
											}
										}
									]
								}
							],
							[
								"answer",
								{
									"__TYPE__": "StructuredTextContent",
									"value": [
										{
											"type": "paragraph",
											"content": {
												"text": "Et anim aliquip voluptate mollit laborum excepteur."
											}
										}
									]
								}
							]
						]
					}
				]
			}
		},
		"items": []
	}
]